xa/__init__.py
xa-0.0.5.dist-info/licenses/LICENSE
xa-0.0.5.dist-info/METADATA
xa-0.0.5.dist-info/WHEEL
xa-0.0.5.dist-info/top_level.txt
xa-0.0.5.dist-info/RECORD
