Metadata-Version: 2.4
Name: xa
Version: 0.0.5
Summary: Accessing information on population in the word.
Home-page: https://github.com/t-c-w/xa
Author: Thor Whalen
License: apache-2.0
Platform: any
License-File: LICENSE
Dynamic: license-file
